README.md
pyproject.toml
setup.py
torch_package/__init__.py
torch_package/model.py
torch_package.egg-info/PKG-INFO
torch_package.egg-info/SOURCES.txt
torch_package.egg-info/dependency_links.txt
torch_package.egg-info/requires.txt
torch_package.egg-info/top_level.txt
torch_package/analysis/__init__.py
torch_package/analysis/visualize.py
torch_package/data/__init__.py
torch_package/data/dataset.py
torch_package/data/transforms/__init__.py
torch_package/data/transforms/blur.py
torch_package/data/transforms/crop.py
torch_package/data/transforms/flip.py
torch_package/data/transforms/rescale.py
torch_package/data/transforms/rotate.py